graders/__init__.py
graders/foo.py
graders-0.0.1a0.dist-info/LICENSE
graders-0.0.1a0.dist-info/METADATA
graders-0.0.1a0.dist-info/WHEEL
graders-0.0.1a0.dist-info/RECORD
