Metadata-Version: 2.1
Name: graders
Version: 0.0.1a0
Summary: This is a template repository for Python projects that use Poetry for their dependency management.
Home-page: https://github.com/nlile/graders
Author: nlile
Author-email: nathan@synthlabs.ai
Requires-Python: >=3.8,<4.0
Classifier: Programming Language :: Python :: 3
Classifier: Programming Language :: Python :: 3.8
Classifier: Programming Language :: Python :: 3.9
Classifier: Programming Language :: Python :: 3.10
Classifier: Programming Language :: Python :: 3.11
Classifier: Programming Language :: Python :: 3.12
Project-URL: Documentation, https://nlile.github.io/graders/
Project-URL: Repository, https://github.com/nlile/graders
